{
  "mode": "intersection_top10_per_day",
  "generated_at_utc": "2025-12-01 14:37:34",
  "timezone": "Asia/Taipei",
  "params": {
    "days": 2,
    "top_n": 10
  },
  "trading_dates": [
    "2025-12-01",
    "2025-11-28"
  ],
  "count_intersection": 2,
  "stocks": [
    {
      "stock_id": "00712",
      "stock_name": "復華富時不動產  ",
      "total_net_buy": 24553,
      "avg_net_buy": 12276.5,
      "per_day": {
        "day1": {
          "date": "2025-12-01",
          "rank": 5,
          "net_buy_lots": 8557
        },
        "day2": {
          "date": "2025-11-28",
          "rank": 3,
          "net_buy_lots": 15996
        }
      }
    },
    {
      "stock_id": "2867",
      "stock_name": "三商壽          ",
      "total_net_buy": 16452,
      "avg_net_buy": 8226.0,
      "per_day": {
        "day1": {
          "date": "2025-12-01",
          "rank": 10,
          "net_buy_lots": 6922
        },
        "day2": {
          "date": "2025-11-28",
          "rank": 5,
          "net_buy_lots": 9530
        }
      }
    }
  ]
}