{
  "mode": "intersection_top10_per_day",
  "generated_at_utc": "2026-06-17 17:23:42",
  "timezone": "Asia/Taipei",
  "params": {
    "days": 2,
    "top_n": 10
  },
  "trading_dates": [
    "2026-06-16",
    "2026-06-15"
  ],
  "count_intersection": 2,
  "stocks": [
    {
      "stock_id": "00403A",
      "stock_name": "主動統一升級50  ",
      "total_net_buy": 443944,
      "avg_net_buy": 221972.0,
      "per_day": {
        "day1": {
          "date": "2026-06-16",
          "rank": 1,
          "net_buy_lots": 151299
        },
        "day2": {
          "date": "2026-06-15",
          "rank": 1,
          "net_buy_lots": 292645
        }
      }
    },
    {
      "stock_id": "2883",
      "stock_name": "凱基金          ",
      "total_net_buy": 49804,
      "avg_net_buy": 24902.0,
      "per_day": {
        "day1": {
          "date": "2026-06-16",
          "rank": 10,
          "net_buy_lots": 18824
        },
        "day2": {
          "date": "2026-06-15",
          "rank": 4,
          "net_buy_lots": 30980
        }
      }
    }
  ],
  "ai_analysis": [
    {
      "ticker": "00403A",
      "name": "主動統一升級50  ",
      "verdict": "建議買進",
      "confidence": "中",
      "reasons": [
        "主動式ETF具三重選股機制強化獲利潛力",
        "台股多頭氣氛帶動相關ETF資金流入"
      ],
      "warning": "主動管理策略效果尚未經長期驗證",
      "next_check": "2023-07-15",
      "data_quality": "有限",
      "net_buy_lots": 443944,
      "is_etf": true
    },
    {
      "ticker": "2883",
      "name": "凱基金",
      "verdict": "謹慎觀察",
      "confidence": "低",
      "reasons": [
        "5月營收年增0%動能疲弱",
        "缺乏近期產業利多或新聞催化"
      ],
      "warning": "營收成長性不足可能壓制股價",
      "next_check": "2024年6月營收",
      "data_quality": "有限",
      "net_buy_lots": 49804,
      "is_etf": false
    }
  ],
  "ai_analysis_time": "2026-06-18 01:21",
  "insti_signal": {
    "buy": [
      {
        "stock_id": "2408",
        "stock_name": "南亞科",
        "foreign_net": 46937,
        "trust_net": 5808,
        "ft_net": 52745,
        "date": "20260616"
      },
      {
        "stock_id": "2344",
        "stock_name": "華邦電",
        "foreign_net": 35105,
        "trust_net": 9429,
        "ft_net": 44534,
        "date": "20260616"
      },
      {
        "stock_id": "2303",
        "stock_name": "聯電",
        "foreign_net": 28998,
        "trust_net": 11348,
        "ft_net": 40346,
        "date": "20260616"
      },
      {
        "stock_id": "2884",
        "stock_name": "玉山金",
        "foreign_net": 32521,
        "trust_net": 702,
        "ft_net": 33223,
        "date": "20260616"
      },
      {
        "stock_id": "5880",
        "stock_name": "合庫金",
        "foreign_net": 30095,
        "trust_net": 990,
        "ft_net": 31085,
        "date": "20260616"
      },
      {
        "stock_id": "2887",
        "stock_name": "台新新光金",
        "foreign_net": 20774,
        "trust_net": 7531,
        "ft_net": 28305,
        "date": "20260616"
      },
      {
        "stock_id": "2883",
        "stock_name": "凱基金",
        "foreign_net": 18824,
        "trust_net": 8045,
        "ft_net": 26869,
        "date": "20260616"
      },
      {
        "stock_id": "2892",
        "stock_name": "第一金",
        "foreign_net": 5558,
        "trust_net": 18826,
        "ft_net": 24384,
        "date": "20260616"
      },
      {
        "stock_id": "1402",
        "stock_name": "遠東新",
        "foreign_net": 8116,
        "trust_net": 13429,
        "ft_net": 21545,
        "date": "20260616"
      },
      {
        "stock_id": "00988A",
        "stock_name": "主動統一全球創新",
        "foreign_net": 2743,
        "trust_net": 10550,
        "ft_net": 13293,
        "date": "20260616"
      }
    ],
    "sell": [
      {
        "stock_id": "2002",
        "stock_name": "中鋼",
        "foreign_net": -25527,
        "trust_net": -396,
        "ft_net": -25923,
        "date": "20260616"
      },
      {
        "stock_id": "2409",
        "stock_name": "友達",
        "foreign_net": -18877,
        "trust_net": -32,
        "ft_net": -18909,
        "date": "20260616"
      },
      {
        "stock_id": "9904",
        "stock_name": "寶成",
        "foreign_net": -9282,
        "trust_net": -2551,
        "ft_net": -11833,
        "date": "20260616"
      },
      {
        "stock_id": "1101",
        "stock_name": "台泥",
        "foreign_net": -10853,
        "trust_net": -286,
        "ft_net": -11139,
        "date": "20260616"
      },
      {
        "stock_id": "3231",
        "stock_name": "緯創",
        "foreign_net": -9014,
        "trust_net": -21,
        "ft_net": -9035,
        "date": "20260616"
      },
      {
        "stock_id": "1504",
        "stock_name": "東元",
        "foreign_net": -5329,
        "trust_net": -622,
        "ft_net": -5951,
        "date": "20260616"
      },
      {
        "stock_id": "2313",
        "stock_name": "華通",
        "foreign_net": -4887,
        "trust_net": -761,
        "ft_net": -5648,
        "date": "20260616"
      },
      {
        "stock_id": "1102",
        "stock_name": "亞泥",
        "foreign_net": -2473,
        "trust_net": -3153,
        "ft_net": -5626,
        "date": "20260616"
      },
      {
        "stock_id": "3042",
        "stock_name": "晶技",
        "foreign_net": -4842,
        "trust_net": -90,
        "ft_net": -4932,
        "date": "20260616"
      },
      {
        "stock_id": "4919",
        "stock_name": "新唐",
        "foreign_net": -4525,
        "trust_net": -50,
        "ft_net": -4575,
        "date": "20260616"
      }
    ],
    "date": "20260616"
  },
  "insti_signal_date": "2026-06-16",
  "market_insti": {
    "date": "20260616",
    "unit": "億元",
    "trust_buy": 386.96,
    "trust_sell": 268.72,
    "trust_net": 118.24,
    "foreign_buy": 4814.99,
    "foreign_sell": 4407.01,
    "foreign_net": 407.98
  },
  "watchlist_summary": [
    {
      "stock_id": "00403A",
      "stock_name": "主動統一升級50",
      "entry_date": "2026-06-18",
      "entry_price": 10.75,
      "latest_price": 10.75,
      "latest_pct": 0.0,
      "latest_date": "2026-06-18",
      "days_tracked": 0
    },
    {
      "stock_id": "2883",
      "stock_name": "凱基金",
      "entry_date": "2026-06-18",
      "entry_price": 30.2,
      "latest_price": 30.2,
      "latest_pct": 0.0,
      "latest_date": "2026-06-18",
      "days_tracked": 0
    },
    {
      "stock_id": "00403A",
      "stock_name": "主動統一升級50",
      "entry_date": "2026-06-17",
      "entry_price": 10.7,
      "latest_price": 10.75,
      "latest_pct": 0.47,
      "latest_date": "2026-06-18",
      "days_tracked": 1
    },
    {
      "stock_id": "2883",
      "stock_name": "凱基金",
      "entry_date": "2026-06-17",
      "entry_price": 29.7,
      "latest_price": 30.2,
      "latest_pct": 1.68,
      "latest_date": "2026-06-18",
      "days_tracked": 1
    },
    {
      "stock_id": "00403A",
      "stock_name": "主動統一升級50",
      "entry_date": "2026-06-16",
      "entry_price": 10.61,
      "latest_price": 10.75,
      "latest_pct": 1.32,
      "latest_date": "2026-06-18",
      "days_tracked": 2
    },
    {
      "stock_id": "00981A",
      "stock_name": "主動統一台股增長",
      "entry_date": "2026-06-16",
      "entry_price": 31.47,
      "latest_price": 30.82,
      "latest_pct": -2.07,
      "latest_date": "2026-06-17",
      "days_tracked": 2
    },
    {
      "stock_id": "2618",
      "stock_name": "長榮航",
      "entry_date": "2026-06-16",
      "entry_price": 39.95,
      "latest_price": 42.55,
      "latest_pct": 6.51,
      "latest_date": "2026-06-18",
      "days_tracked": 2
    },
    {
      "stock_id": "2891",
      "stock_name": "中信金",
      "entry_date": "2026-06-16",
      "entry_price": 70.1,
      "latest_price": 71.0,
      "latest_pct": 1.28,
      "latest_date": "2026-06-18",
      "days_tracked": 2
    },
    {
      "stock_id": "2610",
      "stock_name": "華航",
      "entry_date": "2026-06-16",
      "entry_price": 21.4,
      "latest_price": 21.85,
      "latest_pct": 2.1,
      "latest_date": "2026-06-18",
      "days_tracked": 2
    },
    {
      "stock_id": "2890",
      "stock_name": "永豐金",
      "entry_date": "2026-06-16",
      "entry_price": 35.2,
      "latest_price": 36.35,
      "latest_pct": 3.27,
      "latest_date": "2026-06-18",
      "days_tracked": 2
    },
    {
      "stock_id": "2887",
      "stock_name": "台新新光金",
      "entry_date": "2026-06-14",
      "entry_price": 30.2,
      "latest_price": 32.6,
      "latest_pct": 7.95,
      "latest_date": "2026-06-18",
      "days_tracked": 4
    },
    {
      "stock_id": "2891",
      "stock_name": "中信金",
      "entry_date": "2026-06-14",
      "entry_price": 67.6,
      "latest_price": 71.0,
      "latest_pct": 5.03,
      "latest_date": "2026-06-18",
      "days_tracked": 4
    },
    {
      "stock_id": "2890",
      "stock_name": "永豐金",
      "entry_date": "2026-06-14",
      "entry_price": 34.15,
      "latest_price": 36.35,
      "latest_pct": 6.44,
      "latest_date": "2026-06-18",
      "days_tracked": 4
    },
    {
      "stock_id": "2890",
      "stock_name": "永豐金",
      "entry_date": "2026-06-13",
      "entry_price": 34.15,
      "latest_price": 36.35,
      "latest_pct": 6.44,
      "latest_date": "2026-06-18",
      "days_tracked": 5
    },
    {
      "stock_id": "2892",
      "stock_name": "第一金",
      "entry_date": "2026-06-13",
      "entry_price": 31.0,
      "latest_price": 32.5,
      "latest_pct": 4.84,
      "latest_date": "2026-06-18",
      "days_tracked": 5
    },
    {
      "stock_id": "2801",
      "stock_name": "彰銀",
      "entry_date": "2026-06-13",
      "entry_price": 22.6,
      "latest_price": 22.95,
      "latest_pct": 1.55,
      "latest_date": "2026-06-18",
      "days_tracked": 5
    },
    {
      "stock_id": "2303",
      "stock_name": "聯電",
      "entry_date": "2026-06-12",
      "entry_price": 133.5,
      "latest_price": 140.0,
      "latest_pct": 4.87,
      "latest_date": "2026-06-18",
      "days_tracked": 6
    },
    {
      "stock_id": "2609",
      "stock_name": "陽明",
      "entry_date": "2026-06-12",
      "entry_price": 52.4,
      "latest_price": 51.6,
      "latest_pct": -1.53,
      "latest_date": "2026-06-18",
      "days_tracked": 6
    },
    {
      "stock_id": "3481",
      "stock_name": "群創",
      "entry_date": "2026-06-12",
      "entry_price": 48.55,
      "latest_price": 58.6,
      "latest_pct": 20.7,
      "latest_date": "2026-06-18",
      "days_tracked": 6
    },
    {
      "stock_id": "2887",
      "stock_name": "台新新光金",
      "entry_date": "2026-06-12",
      "entry_price": 30.2,
      "latest_price": 32.6,
      "latest_pct": 7.95,
      "latest_date": "2026-06-18",
      "days_tracked": 6
    },
    {
      "stock_id": "2892",
      "stock_name": "第一金",
      "entry_date": "2026-06-11",
      "entry_price": 30.55,
      "latest_price": 32.5,
      "latest_pct": 6.38,
      "latest_date": "2026-06-18",
      "days_tracked": 7
    },
    {
      "stock_id": "2801",
      "stock_name": "彰銀",
      "entry_date": "2026-06-11",
      "entry_price": 22.35,
      "latest_price": 22.95,
      "latest_pct": 2.68,
      "latest_date": "2026-06-18",
      "days_tracked": 7
    },
    {
      "stock_id": "2890",
      "stock_name": "永豐金",
      "entry_date": "2026-06-10",
      "entry_price": 34.25,
      "latest_price": 36.35,
      "latest_pct": 6.13,
      "latest_date": "2026-06-18",
      "days_tracked": 8
    },
    {
      "stock_id": "2303",
      "stock_name": "聯電",
      "entry_date": "2026-06-09",
      "entry_price": 121.0,
      "latest_price": 140.0,
      "latest_pct": 15.7,
      "latest_date": "2026-06-18",
      "days_tracked": 9
    },
    {
      "stock_id": "00953B",
      "stock_name": "群益優選非投等債",
      "entry_date": "2026-06-09",
      "entry_price": 9.55,
      "latest_price": 9.61,
      "latest_pct": 0.63,
      "latest_date": "2026-06-18",
      "days_tracked": 9
    },
    {
      "stock_id": "2609",
      "stock_name": "陽明",
      "entry_date": "2026-06-09",
      "entry_price": 51.7,
      "latest_price": 51.6,
      "latest_pct": -0.19,
      "latest_date": "2026-06-18",
      "days_tracked": 9
    },
    {
      "stock_id": "2881",
      "stock_name": "富邦金",
      "entry_date": "2026-06-08",
      "entry_price": 113.0,
      "latest_price": 135.5,
      "latest_pct": 19.91,
      "latest_date": "2026-06-18",
      "days_tracked": 10
    },
    {
      "stock_id": "2882",
      "stock_name": "國泰金",
      "entry_date": "2026-06-08",
      "entry_price": 94.3,
      "latest_price": 113.5,
      "latest_pct": 20.36,
      "latest_date": "2026-06-18",
      "days_tracked": 10
    }
  ]
}